streamlit_heroku/__init__.py
streamlit_heroku/main.py
streamlit_heroku-0.0.2.data/scripts/streamlit_heroku
streamlit_heroku-0.0.2.dist-info/LICENSE
streamlit_heroku-0.0.2.dist-info/METADATA
streamlit_heroku-0.0.2.dist-info/WHEEL
streamlit_heroku-0.0.2.dist-info/top_level.txt
streamlit_heroku-0.0.2.dist-info/RECORD
